onemap_py/__init__.py
onemap_py/auth.py
onemap_py/base.py
onemap_py/planning_areas.py
onemap_py/population.py
onemap_py/routing.py
onemap_py/themes.py
onemap_py-0.2.0.dist-info/WHEEL
onemap_py-0.2.0.dist-info/METADATA
onemap_py-0.2.0.dist-info/RECORD
