Metadata-Version: 2.1
Name: onemap-py
Version: 0.2.0
Summary: Python wrapper for SLA's OneMap API
Home-page: https://github.com/tauhlim/onemap-py
Author: tauculator
Requires-Python: >=3.6,<4.0
Classifier: Programming Language :: Python :: 3
Classifier: Programming Language :: Python :: 3.6
Classifier: Programming Language :: Python :: 3.7
Classifier: Programming Language :: Python :: 3.8
Requires-Dist: pypolyline (>=0.2.4,<0.3.0)
Project-URL: Repository, https://github.com/tauhlim/onemap-py
